LICENSE
duo_cli/__init__.py
duo_cli/cli.py
duo_cli/ios_backup.py
duo_cli/main.py
duo_cli-0.1.0.dist-info/entry_points.txt
duo_cli-0.1.0.dist-info/LICENSE
duo_cli-0.1.0.dist-info/WHEEL
duo_cli-0.1.0.dist-info/METADATA
duo_cli-0.1.0.dist-info/RECORD
