Metadata-Version: 2.1
Name: duo-cli
Version: 0.1.0
Summary: Duo Mobile CLI for generating TOTP codes.
Home-page: https://github.com/nathancahill/duo-cli
License: MIT
Keywords: totp,duo,otp,cli
Author: Nathan Cahill
Author-email: nathan@nathancahill.com
Requires-Python: >=3.6,<4.0
Classifier: Environment :: Console
Classifier: License :: OSI Approved :: MIT License
Classifier: Programming Language :: Python :: 3
Classifier: Programming Language :: Python :: 3.6
Classifier: Programming Language :: Python :: 3.7
Classifier: Programming Language :: Python :: 3.8
Classifier: Programming Language :: Python :: 3.9
Requires-Dist: PyInquirer (>=1.0.3,<2.0.0)
Requires-Dist: PyNaCl (>=1.4.0,<2.0.0)
Requires-Dist: click (>=7.1.2,<8.0.0)
Requires-Dist: passlib (>=1.7.4,<2.0.0)
Requires-Dist: pyperclip (>=1.8.2,<2.0.0)
Requires-Dist: rich (>=10.1.0,<11.0.0)
Project-URL: Repository, https://github.com/nathancahill/duo-cli
